testy/__init__.py
testy/async_support.py
testy/cli.py
testy/core.py
testy/lifecycle.py
testy/parameterized.py
testy_test_python_framework-0.1.0.dist-info/METADATA
testy_test_python_framework-0.1.0.dist-info/WHEEL
testy_test_python_framework-0.1.0.dist-info/entry_points.txt
testy_test_python_framework-0.1.0.dist-info/top_level.txt
testy_test_python_framework-0.1.0.dist-info/RECORD
